[{"geometry": {"type": "Point", "coordinates": ["0.2008709", "47.9767112"]}, "type": "Feature", "properties": {"street": "1 RUE ADELINE CHIPPARD , 72000 Le Mans, France", "filename": "/Users/blain/Private/projects/github/haum/dataelections/data/secteurs/sect_68.csv"}}, {"geometry": {"type": "Point", "coordinates": ["0.2019819", "47.9762365"]}, "type": "Feature", "properties": {"street": "68 RUE ADELINE CHIPPARD , 72000 Le Mans, France", "filename": "/Users/blain/Private/projects/github/haum/dataelections/data/secteurs/sect_68.csv"}}, {"geometry": {"type": "Point", "coordinates": ["0.2045983", "47.970606"]}, "type": "Feature", "properties": {"street": "1 RUE ALBERT THOMAS , 72000 Le Mans, France", "filename": "/Users/blain/Private/projects/github/haum/dataelections/data/secteurs/sect_68.csv"}}, {"geometry": {"type": "Point", "coordinates": ["0.2030467", "47.9708868"]}, "type": "Feature", "properties": {"street": "68 RUE ALBERT THOMAS , 72000 Le Mans, France", "filename": "/Users/blain/Private/projects/github/haum/dataelections/data/secteurs/sect_68.csv"}}, {"geometry": {"type": "Point", "coordinates": ["0.2000387", "47.9762792"]}, "type": "Feature", "properties": {"street": "1 RUE ALFRED KASTLER , 72000 Le Mans, France", "filename": "/Users/blain/Private/projects/github/haum/dataelections/data/secteurs/sect_68.csv"}}, {"geometry": {"type": "Point", "coordinates": ["0.201502", "47.9758312"]}, "type": "Feature", "properties": {"street": "68 RUE ALFRED KASTLER , 72000 Le Mans, France", "filename": "/Users/blain/Private/projects/github/haum/dataelections/data/secteurs/sect_68.csv"}}, {"geometry": {"type": "Point", "coordinates": ["0.1609266", "48.0157803"]}, "type": "Feature", "properties": {"street": "12 RUE D' AUNIS , 72000 Le Mans, France", "filename": "/Users/blain/Private/projects/github/haum/dataelections/data/secteurs/sect_68.csv"}}, {"geometry": {"type": "Point", "coordinates": ["0.1609266", "48.0157803"]}, "type": "Feature", "properties": {"street": "9 RUE D' AUNIS , 72000 Le Mans, France", "filename": "/Users/blain/Private/projects/github/haum/dataelections/data/secteurs/sect_68.csv"}}, {"geometry": {"type": "Point", "coordinates": ["0.2034166", "47.9734462"]}, "type": "Feature", "properties": {"street": "1 RUE DE BEAUCE , 72000 Le Mans, France", "filename": "/Users/blain/Private/projects/github/haum/dataelections/data/secteurs/sect_68.csv"}}, {"geometry": {"type": "Point", "coordinates": ["0.2029689", "47.972676"]}, "type": "Feature", "properties": {"street": "8 RUE DE BEAUCE , 72000 Le Mans, France", "filename": "/Users/blain/Private/projects/github/haum/dataelections/data/secteurs/sect_68.csv"}}, {"geometry": {"type": "Point", "coordinates": ["0.2034251", "47.9734566"]}, "type": "Feature", "properties": {"street": "1 RUE BLANCHARD , 72000 Le Mans, France", "filename": "/Users/blain/Private/projects/github/haum/dataelections/data/secteurs/sect_68.csv"}}, {"geometry": {"type": "Point", "coordinates": ["0.2033306", "47.9735007"]}, "type": "Feature", "properties": {"street": "68 RUE BLANCHARD , 72000 Le Mans, France", "filename": "/Users/blain/Private/projects/github/haum/dataelections/data/secteurs/sect_68.csv"}}, {"geometry": {"type": "Point", "coordinates": ["0.1992971", "47.9734819"]}, "type": "Feature", "properties": {"street": "1 AVENUE DE BRETAGNE , 72000 Le Mans, France", "filename": "/Users/blain/Private/projects/github/haum/dataelections/data/secteurs/sect_68.csv"}}, {"geometry": {"type": "Point", "coordinates": ["0.1973144", "47.9675297"]}, "type": "Feature", "properties": {"street": "68 AVENUE DE BRETAGNE , 72000 Le Mans, France", "filename": "/Users/blain/Private/projects/github/haum/dataelections/data/secteurs/sect_68.csv"}}, {"geometry": {"type": "Point", "coordinates": ["0.202982", "47.9771922"]}, "type": "Feature", "properties": {"street": "1 RUE DE LA COLLECTIVITE , 72000 Le Mans, France", "filename": "/Users/blain/Private/projects/github/haum/dataelections/data/secteurs/sect_68.csv"}}, {"geometry": {"type": "Point", "coordinates": ["0.2007984", "47.9784769"]}, "type": "Feature", "properties": {"street": "68 RUE DE LA COLLECTIVITE , 72000 Le Mans, France", "filename": "/Users/blain/Private/projects/github/haum/dataelections/data/secteurs/sect_68.csv"}}, {"geometry": {"type": "Point", "coordinates": ["0.2024184", "47.9733836"]}, "type": "Feature", "properties": {"street": "1 RUE DU COTENTIN , 72000 Le Mans, France", "filename": "/Users/blain/Private/projects/github/haum/dataelections/data/secteurs/sect_68.csv"}}, {"geometry": {"type": "Point", "coordinates": ["0.202315", "47.9728269"]}, "type": "Feature", "properties": {"street": "7 RUE DU COTENTIN , 72000 Le Mans, France", "filename": "/Users/blain/Private/projects/github/haum/dataelections/data/secteurs/sect_68.csv"}}, {"geometry": {"type": "Point", "coordinates": ["0.2014757", "47.9791169"]}, "type": "Feature", "properties": {"street": "1 RUE DENIS PAPIN , 72000 Le Mans, France", "filename": "/Users/blain/Private/projects/github/haum/dataelections/data/secteurs/sect_68.csv"}}, {"geometry": {"type": "Point", "coordinates": ["0.1995406", "47.9743758"]}, "type": "Feature", "properties": {"street": "89 RUE DENIS PAPIN , 72000 Le Mans, France", "filename": "/Users/blain/Private/projects/github/haum/dataelections/data/secteurs/sect_68.csv"}}, {"geometry": {"type": "Point", "coordinates": ["0.2038041", "47.9707897"]}, "type": "Feature", "properties": {"street": "1 RUE DU DOCTEUR CALMETTE , 72000 Le Mans, France", "filename": "/Users/blain/Private/projects/github/haum/dataelections/data/secteurs/sect_68.csv"}}, {"geometry": {"type": "Point", "coordinates": ["0.2024436", "47.9681902"]}, "type": "Feature", "properties": {"street": "68 RUE DU DOCTEUR CALMETTE , 72000 Le Mans, France", "filename": "/Users/blain/Private/projects/github/haum/dataelections/data/secteurs/sect_68.csv"}}, {"geometry": {"type": "Point", "coordinates": ["0.2037763", "47.9708122"]}, "type": "Feature", "properties": {"street": "1 RUE DU DOCTEUR ROUX , 72000 Le Mans, France", "filename": "/Users/blain/Private/projects/github/haum/dataelections/data/secteurs/sect_68.csv"}}, {"geometry": {"type": "Point", "coordinates": ["0.2047096", "47.9727126"]}, "type": "Feature", "properties": {"street": "68 RUE DU DOCTEUR ROUX , 72000 Le Mans, France", "filename": "/Users/blain/Private/projects/github/haum/dataelections/data/secteurs/sect_68.csv"}}, {"geometry": {"type": "Point", "coordinates": ["0.2030636", "47.971919"]}, "type": "Feature", "properties": {"street": "1 RUE DE GUYENNE , 72000 Le Mans, France", "filename": "/Users/blain/Private/projects/github/haum/dataelections/data/secteurs/sect_68.csv"}}, {"geometry": {"type": "Point", "coordinates": ["0.2036316", "47.9718678"]}, "type": "Feature", "properties": {"street": "7 RUE DE GUYENNE , 72000 Le Mans, France", "filename": "/Users/blain/Private/projects/github/haum/dataelections/data/secteurs/sect_68.csv"}}, {"geometry": {"type": "Point", "coordinates": ["0.1609266", "48.0157803"]}, "type": "Feature", "properties": {"street": "1 RUE DE L' ILE DE FRANCE , 72000 Le Mans, France", "filename": "/Users/blain/Private/projects/github/haum/dataelections/data/secteurs/sect_68.csv"}}, {"geometry": {"type": "Point", "coordinates": ["0.1609266", "48.0157803"]}, "type": "Feature", "properties": {"street": "68 RUE DE L' ILE DE FRANCE , 72000 Le Mans, France", "filename": "/Users/blain/Private/projects/github/haum/dataelections/data/secteurs/sect_68.csv"}}, {"geometry": {"type": "Point", "coordinates": ["0.2051482", "47.9786689"]}, "type": "Feature", "properties": {"street": "145 BOULEVARD JEAN JACQUES ROUSSEAU , 72000 Le Mans, France", "filename": "/Users/blain/Private/projects/github/haum/dataelections/data/secteurs/sect_68.csv"}}, {"geometry": {"type": "Point", "coordinates": ["0.2054621", "47.9794349"]}, "type": "Feature", "properties": {"street": "68 BOULEVARD JEAN JACQUES ROUSSEAU , 72000 Le Mans, France", "filename": "/Users/blain/Private/projects/github/haum/dataelections/data/secteurs/sect_68.csv"}}, {"geometry": {"type": "Point", "coordinates": ["0.2025", "47.9769771"]}, "type": "Feature", "properties": {"street": "1 RUE JULES FERRY , 72000 Le Mans, France", "filename": "/Users/blain/Private/projects/github/haum/dataelections/data/secteurs/sect_68.csv"}}, {"geometry": {"type": "Point", "coordinates": ["0.2006419", "47.9780867"]}, "type": "Feature", "properties": {"street": "68 RUE JULES FERRY , 72000 Le Mans, France", "filename": "/Users/blain/Private/projects/github/haum/dataelections/data/secteurs/sect_68.csv"}}, {"geometry": {"type": "Point", "coordinates": ["0.1999955", "47.9729524"]}, "type": "Feature", "properties": {"street": "1 RUE DU MAINE , 72000 Le Mans, France", "filename": "/Users/blain/Private/projects/github/haum/dataelections/data/secteurs/sect_68.csv"}}, {"geometry": {"type": "Point", "coordinates": ["0.1988239", "47.9692255"]}, "type": "Feature", "properties": {"street": "68 RUE DU MAINE , 72000 Le Mans, France", "filename": "/Users/blain/Private/projects/github/haum/dataelections/data/secteurs/sect_68.csv"}}, {"geometry": {"type": "Point", "coordinates": ["0.2003788", "47.9723873"]}, "type": "Feature", "properties": {"street": "1 RUE DU PERCHE , 72000 Le Mans, France", "filename": "/Users/blain/Private/projects/github/haum/dataelections/data/secteurs/sect_68.csv"}}, {"geometry": {"type": "Point", "coordinates": ["0.1994961", "47.9721747"]}, "type": "Feature", "properties": {"street": "68 RUE DU PERCHE , 72000 Le Mans, France", "filename": "/Users/blain/Private/projects/github/haum/dataelections/data/secteurs/sect_68.csv"}}, {"geometry": {"type": "Point", "coordinates": ["0.1998184", "47.9736729"]}, "type": "Feature", "properties": {"street": "1 AVENUE PIERRE SEMARD , 72000 Le Mans, France", "filename": "/Users/blain/Private/projects/github/haum/dataelections/data/secteurs/sect_68.csv"}}, {"geometry": {"type": "Point", "coordinates": ["0.2042165", "47.9720564"]}, "type": "Feature", "properties": {"street": "68 AVENUE PIERRE SEMARD , 72000 Le Mans, France", "filename": "/Users/blain/Private/projects/github/haum/dataelections/data/secteurs/sect_68.csv"}}, {"geometry": {"type": "Point", "coordinates": ["0.2004016", "47.9721806"]}, "type": "Feature", "properties": {"street": "12 RUE DU POITOU , 72000 Le Mans, France", "filename": "/Users/blain/Private/projects/github/haum/dataelections/data/secteurs/sect_68.csv"}}, {"geometry": {"type": "Point", "coordinates": ["0.2004192", "47.9720556"]}, "type": "Feature", "properties": {"street": "68 RUE DU POITOU , 72000 Le Mans, France", "filename": "/Users/blain/Private/projects/github/haum/dataelections/data/secteurs/sect_68.csv"}}, {"geometry": {"type": "Point", "coordinates": ["0.2004639", "47.971193"]}, "type": "Feature", "properties": {"street": "22 RUE DE TOURAINE , 72000 Le Mans, France", "filename": "/Users/blain/Private/projects/github/haum/dataelections/data/secteurs/sect_68.csv"}}, {"geometry": {"type": "Point", "coordinates": ["0.2013848", "47.971857"]}, "type": "Feature", "properties": {"street": "7 RUE DE TOURAINE , 72000 Le Mans, France", "filename": "/Users/blain/Private/projects/github/haum/dataelections/data/secteurs/sect_68.csv"}}, {"geometry": {"type": "Point", "coordinates": ["0.2003967", "47.973483"]}, "type": "Feature", "properties": {"street": "1 RUE DU VAL DE LOIR , 72000 Le Mans, France", "filename": "/Users/blain/Private/projects/github/haum/dataelections/data/secteurs/sect_68.csv"}}, {"geometry": {"type": "Point", "coordinates": ["0.2054448", "47.9724406"]}, "type": "Feature", "properties": {"street": "68 RUE DU VAL DE LOIR , 72000 Le Mans, France", "filename": "/Users/blain/Private/projects/github/haum/dataelections/data/secteurs/sect_68.csv"}}, {"geometry": {"type": "Point", "coordinates": ["0.2026402", "47.9707474"]}, "type": "Feature", "properties": {"street": "1 PLACE DE LA VENDEE , 72000 Le Mans, France", "filename": "/Users/blain/Private/projects/github/haum/dataelections/data/secteurs/sect_68.csv"}}, {"geometry": {"type": "Point", "coordinates": ["0.2028628", "47.9707767"]}, "type": "Feature", "properties": {"street": "68 PLACE DE LA VENDEE , 72000 Le Mans, France", "filename": "/Users/blain/Private/projects/github/haum/dataelections/data/secteurs/sect_68.csv"}}]